README.md
setup.py
nba_scrape/__init__.py
nba_scrape/constants.py
nba_scrape/entities.py
nba_scrape/helpers.py
nba_scrape/nba.py
nba_scrape/nba_exceptions.py
nba_scrape.egg-info/PKG-INFO
nba_scrape.egg-info/SOURCES.txt
nba_scrape.egg-info/dependency_links.txt
nba_scrape.egg-info/requires.txt
nba_scrape.egg-info/top_level.txt