Metadata-Version: 1.1
Name: nba-scrape
Version: 0.56
Summary: Python utility to easily scrape NBA stats
Home-page: https://github.com/hqadeer/nba_scrape.git
Author: Hamza Qadeer
Author-email: hamza.qadeer@berkeley.edu
License: UNKNOWN
Platform: UNKNOWN
Classifier: Programming Language :: Python :: 3
Classifier: License :: OSI Approved :: MIT License
Classifier: Operating System :: OS Independent
